{
  "db_name": "PostgreSQL",
  "query": "SELECT id, email, password, totp_enabled, totp_secret, username FROM users WHERE id = $1",
  "describe": {
    "columns": [
      {
        "ordinal": 0,
        "name": "id",
        "type_info": "Int4"
      },
      {
        "ordinal": 1,
        "name": "email",
        "type_info": "Varchar"
      },
      {
        "ordinal": 2,
        "name": "password",
        "type_info": "Varchar"
      },
      {
        "ordinal": 3,
        "name": "totp_enabled",
        "type_info": "Bool"
      },
      {
        "ordinal": 4,
        "name": "totp_secret",
        "type_info": "Text"
      },
      {
        "ordinal": 5,
        "name": "username",
        "type_info": "Varchar"
      }
    ],
    "parameters": {
      "Left": [
        "Int4"
      ]
    },
    "nullable": [
      false,
      true,
      false,
      true,
      true,
      false
    ]
  },
  "hash": "0eeeac1ec50c6d2239e08e1b732e0796dc5143ac4c8a06879c8dc1f3a67bc515"
}
